{
  "id": 12624355,
  "name": "Bruce L. SMALL, petitioner, v. FLORIDA.",
  "name_abbreviation": "Small v. Florida",
  "decision_date": "2018-10-01",
  "docket_number": "No. 17\u20138843.",
  "first_page": "84",
  "last_page": "84",
  "citations": [
    {
      "type": "official",
      "cite": "139 S. Ct. 84"
    },
    {
      "type": "parallel",
      "cite": "202 L. Ed. 2d 55"
    }
  ],
  "court": {
    "name_abbreviation": "U.S.",
    "id": 9009,
    "name": "Supreme Court of the United States"
  },
  "jurisdiction": {
    "id": 39,
    "name_long": "United States",
    "name": "U.S."
  },
  "cites_to": [],
  "analysis": {
    "cardinality": 26,
    "char_count": 202,
    "sha256": "5a04c3312a6ee8da9a098922b618e03ae0c28737c1b1047ba9595ab02cb4b483",
    "simhash": "1:716e4214f8d5448d",
    "word_count": 33
  },
  "last_updated": "2021-09-08T21:16:17.237805+00:00",
  "provenance": {
    "date_added": "2021-08-27",
    "source": "Fastcase",
    "batch": "2021"
  },
  "casebody": {
    "judges": [],
    "parties": [
      "Bruce L. SMALL, petitioner,\nv.\nFLORIDA."
    ],
    "opinions": [
      {
        "text": "",
        "type": "majority",
        "author": null
      }
    ],
    "attorneys": [],
    "corrections": "",
    "head_matter": "Bruce L. SMALL, petitioner,\nv.\nFLORIDA.\nNo. 17-8843.\nSupreme Court of the United States\nOct. 1, 2018.\nPetition for writ of certiorari to the District Court of Appeal of Florida, Third District denied."
  },
  "file_name": "0084-01",
  "first_page_order": 84,
  "last_page_order": 84
}
