{
  "id": 12619414,
  "name": "In Re Daniel Eric SALLEY, petitioner.",
  "name_abbreviation": "In re Salley",
  "decision_date": "2019-04-15",
  "docket_number": "No. 18\u20137939.",
  "first_page": "1561",
  "last_page": "1561",
  "citations": [
    {
      "type": "official",
      "cite": "139 S. Ct. 1561"
    }
  ],
  "court": {
    "name_abbreviation": "U.S.",
    "id": 9009,
    "name": "Supreme Court of the United States"
  },
  "jurisdiction": {
    "id": 39,
    "name_long": "United States",
    "name": "U.S."
  },
  "cites_to": [],
  "analysis": {
    "cardinality": 30,
    "char_count": 218,
    "sha256": "dffe20cd54f4c5abcd03a7f2aae4ce456750acefb70987a943449ff5ef8d5853",
    "simhash": "1:e9e37e4eefcad9cf",
    "word_count": 36
  },
  "last_updated": "2021-08-27T21:04:40.883505+00:00",
  "provenance": {
    "date_added": "2021-08-27",
    "source": "Fastcase",
    "batch": "2021"
  },
  "casebody": {
    "judges": [],
    "parties": [
      "In Re Daniel Eric SALLEY, petitioner."
    ],
    "opinions": [
      {
        "text": "Justice KAGAN took no part in the consideration or decision of this petition.",
        "type": "majority",
        "author": "Justice KAGAN took no part in the consideration or decision of this petition."
      }
    ],
    "attorneys": [
      "Petition for writ of mandamus denied."
    ],
    "corrections": "",
    "head_matter": "In Re Daniel Eric SALLEY, petitioner.\nNo. 18-7939.\nSupreme Court of the United States\nApril 15, 2019.\nPetition for writ of mandamus denied."
  },
  "file_name": "1561-04",
  "first_page_order": 1561,
  "last_page_order": 1561
}
