{
  "id": 12599986,
  "name": "Valiant WHITE, petitioner, v. Jeffrey WOODS, Warden.",
  "name_abbreviation": "White v. Woods",
  "decision_date": "2015-10-05",
  "docket_number": "No. 14\u20139479.",
  "first_page": "39",
  "last_page": "39",
  "citations": [
    {
      "type": "official",
      "cite": "136 S. Ct. 39"
    },
    {
      "type": "parallel",
      "cite": "193 L. Ed. 2d 50"
    }
  ],
  "court": {
    "name_abbreviation": "U.S.",
    "id": 9009,
    "name": "Supreme Court of the United States"
  },
  "jurisdiction": {
    "id": 39,
    "name_long": "United States",
    "name": "U.S."
  },
  "cites_to": [],
  "analysis": {
    "cardinality": 27,
    "char_count": 216,
    "sha256": "1a69978a6b0ce06c88ae7cae6e6b09a217039ca1b89329b9c1b3e278df85fca5",
    "simhash": "1:e5ad56043accd4bd",
    "word_count": 35
  },
  "last_updated": "2021-08-27T21:04:35.133232+00:00",
  "provenance": {
    "date_added": "2021-08-27",
    "source": "Fastcase",
    "batch": "2021"
  },
  "casebody": {
    "judges": [],
    "parties": [
      "Valiant WHITE, petitioner,\nv.\nJeffrey WOODS, Warden."
    ],
    "opinions": [
      {
        "text": "",
        "type": "majority",
        "author": null
      }
    ],
    "attorneys": [
      "Petition for writ of certiorari to the United States Court of Appeals for the Sixth Circuit denied."
    ],
    "corrections": "",
    "head_matter": "Valiant WHITE, petitioner,\nv.\nJeffrey WOODS, Warden.\nNo. 14-9479.\nSupreme Court of the United States\nOct. 5, 2015.\nPetition for writ of certiorari to the United States Court of Appeals for the Sixth Circuit denied."
  },
  "file_name": "0039-03",
  "first_page_order": 39,
  "last_page_order": 39
}
