{
  "id": 12599837,
  "name": "Sandra Sue GRAZZINI-RUCKI, Individually and on Behalf of Her Children, N.J.R., S.V.R., G.J.R., N.G.R., and G.P.R., petitioner, v. David KNUTSON, et al.",
  "name_abbreviation": "Grazzini-Rucki ex rel. Children v. Knutson",
  "decision_date": "2015-10-19",
  "docket_number": "No. 15\u2013220.",
  "first_page": "361",
  "last_page": "361",
  "citations": [
    {
      "type": "official",
      "cite": "136 S. Ct. 361"
    },
    {
      "type": "parallel",
      "cite": "193 L. Ed. 2d 290"
    }
  ],
  "court": {
    "name_abbreviation": "U.S.",
    "id": 9009,
    "name": "Supreme Court of the United States"
  },
  "jurisdiction": {
    "id": 39,
    "name_long": "United States",
    "name": "U.S."
  },
  "cites_to": [],
  "analysis": {
    "cardinality": 40,
    "char_count": 316,
    "sha256": "4f50ee691e1a91542011f4ba0d24b19f4b10d773dc1288d0cf960b596a734200",
    "simhash": "1:40bddc52bc0383bd",
    "word_count": 50
  },
  "last_updated": "2021-09-08T21:16:17.237805+00:00",
  "provenance": {
    "date_added": "2021-08-27",
    "source": "Fastcase",
    "batch": "2021"
  },
  "casebody": {
    "judges": [],
    "parties": [
      "Sandra Sue GRAZZINI-RUCKI, Individually and on Behalf of Her Children, N.J.R., S.V.R., G.J.R., N.G.R., and G.P.R., petitioner,\nv.\nDavid KNUTSON, et al."
    ],
    "opinions": [
      {
        "text": "",
        "type": "majority",
        "author": null
      }
    ],
    "attorneys": [
      "Petition for writ of certiorari to the United States Court of Appeals for the Eighth Circuit denied."
    ],
    "corrections": "",
    "head_matter": "Sandra Sue GRAZZINI-RUCKI, Individually and on Behalf of Her Children, N.J.R., S.V.R., G.J.R., N.G.R., and G.P.R., petitioner,\nv.\nDavid KNUTSON, et al.\nNo. 15-220.\nSupreme Court of the United States\nOct. 19, 2015.\nPetition for writ of certiorari to the United States Court of Appeals for the Eighth Circuit denied."
  },
  "file_name": "0361-05",
  "first_page_order": 361,
  "last_page_order": 361
}
