{
  "id": 12600216,
  "name": "Jeffrey Bernard JOYNER, petitioner, v. UNITED STATES.",
  "name_abbreviation": "Joyner v. United States",
  "decision_date": "2015-11-02",
  "docket_number": "No. 15\u20136374.",
  "first_page": "433",
  "last_page": "433",
  "citations": [
    {
      "type": "official",
      "cite": "136 S. Ct. 433"
    },
    {
      "type": "parallel",
      "cite": "193 L. Ed. 2d 337"
    }
  ],
  "court": {
    "name_abbreviation": "U.S.",
    "id": 9009,
    "name": "Supreme Court of the United States"
  },
  "jurisdiction": {
    "id": 39,
    "name_long": "United States",
    "name": "U.S."
  },
  "cites_to": [],
  "analysis": {
    "cardinality": 25,
    "char_count": 218,
    "sha256": "5adf9a9a0b02e3587bc806dee5947c7f45b0f1eca93867964ae30c442493800d",
    "simhash": "1:13ad36443b84870d",
    "word_count": 35
  },
  "last_updated": "2021-09-08T21:16:17.237805+00:00",
  "provenance": {
    "date_added": "2021-08-27",
    "source": "Fastcase",
    "batch": "2021"
  },
  "casebody": {
    "judges": [],
    "parties": [
      "Jeffrey Bernard JOYNER, petitioner,\nv.\nUNITED STATES."
    ],
    "opinions": [
      {
        "text": "",
        "type": "majority",
        "author": null
      }
    ],
    "attorneys": [
      "Petition for writ of certiorari to the United States Court of Appeals for the Fourth Circuit denied."
    ],
    "corrections": "",
    "head_matter": "Jeffrey Bernard JOYNER, petitioner,\nv.\nUNITED STATES.\nNo. 15-6374.\nSupreme Court of the United States\nNov. 2, 2015.\nPetition for writ of certiorari to the United States Court of Appeals for the Fourth Circuit denied."
  },
  "file_name": "0433-04",
  "first_page_order": 433,
  "last_page_order": 433
}
