{
  "id": 12600380,
  "name": "Ronald J. HAMILTON, Jr., petitioner, v. Angelita SMARJESSE, et al.",
  "name_abbreviation": "Hamilton v. Smarjesse",
  "decision_date": "2015-11-09",
  "docket_number": "No. 15\u20136179.",
  "first_page": "489",
  "last_page": "489",
  "citations": [
    {
      "type": "official",
      "cite": "136 S. Ct. 489"
    },
    {
      "type": "parallel",
      "cite": "193 L. Ed. 2d 357"
    }
  ],
  "court": {
    "name_abbreviation": "U.S.",
    "id": 9009,
    "name": "Supreme Court of the United States"
  },
  "jurisdiction": {
    "id": 39,
    "name_long": "United States",
    "name": "U.S."
  },
  "cites_to": [],
  "analysis": {
    "cardinality": 30,
    "char_count": 231,
    "sha256": "7182e4b64dbbaddfc87b6570e13f7b963e89e40e27e273b460a50a6a7bead0f9",
    "simhash": "1:023ff674af8c27a9",
    "word_count": 38
  },
  "last_updated": "2021-08-27T21:04:35.133232+00:00",
  "provenance": {
    "date_added": "2021-08-27",
    "source": "Fastcase",
    "batch": "2021"
  },
  "casebody": {
    "judges": [],
    "parties": [
      "Ronald J. HAMILTON, Jr., petitioner,\nv.\nAngelita SMARJESSE, et al."
    ],
    "opinions": [
      {
        "text": "",
        "type": "majority",
        "author": null
      }
    ],
    "attorneys": [
      "Petition for writ of certiorari to the United States Court of Appeals for the Eighth Circuit denied."
    ],
    "corrections": "",
    "head_matter": "Ronald J. HAMILTON, Jr., petitioner,\nv.\nAngelita SMARJESSE, et al.\nNo. 15-6179.\nSupreme Court of the United States\nNov. 9, 2015.\nPetition for writ of certiorari to the United States Court of Appeals for the Eighth Circuit denied."
  },
  "file_name": "0489-01",
  "first_page_order": 489,
  "last_page_order": 489
}
