{
  "id": 12595015,
  "name": "WAL-MART STORES, INC., petitioner, v. Cheryl PHIPPS, et al.",
  "name_abbreviation": "Wal-Mart Stores, Inc. v. Phipps",
  "decision_date": "2016-02-29",
  "docket_number": "No. 15\u2013597.",
  "first_page": "1163",
  "last_page": "1163",
  "citations": [
    {
      "type": "official",
      "cite": "136 S. Ct. 1163"
    },
    {
      "type": "parallel",
      "cite": "194 L. Ed. 2d 176"
    }
  ],
  "court": {
    "name_abbreviation": "U.S.",
    "id": 9009,
    "name": "Supreme Court of the United States"
  },
  "jurisdiction": {
    "id": 39,
    "name_long": "United States",
    "name": "U.S."
  },
  "cites_to": [],
  "analysis": {
    "cardinality": 29,
    "char_count": 223,
    "sha256": "899ec04a215556d632496705bbc7d0dc5bedc0139289c4ffb4b4dad9060cb081",
    "simhash": "1:f8afd6469b654631",
    "word_count": 37
  },
  "last_updated": "2021-09-08T21:16:17.237805+00:00",
  "provenance": {
    "date_added": "2021-08-27",
    "source": "Fastcase",
    "batch": "2021"
  },
  "casebody": {
    "judges": [],
    "parties": [
      "WAL-MART STORES, INC., petitioner,\nv.\nCheryl PHIPPS, et al."
    ],
    "opinions": [
      {
        "text": "",
        "type": "majority",
        "author": null
      }
    ],
    "attorneys": [
      "Petition for writ of certiorari to the United States Court of Appeals for the Sixth Circuit denied."
    ],
    "corrections": "",
    "head_matter": "WAL-MART STORES, INC., petitioner,\nv.\nCheryl PHIPPS, et al.\nNo. 15-597.\nSupreme Court of the United States\nFeb. 29, 2016.\nPetition for writ of certiorari to the United States Court of Appeals for the Sixth Circuit denied."
  },
  "file_name": "1163-05",
  "first_page_order": 1163,
  "last_page_order": 1163
}
