{
  "id": 12595062,
  "name": "Steven Michael BACKSTROM, petitioner, v. TEXAS.",
  "name_abbreviation": "Backstrom v. Texas",
  "decision_date": "2016-02-29",
  "docket_number": "No. 15\u20137157.",
  "first_page": "1170",
  "last_page": "1170",
  "citations": [
    {
      "type": "official",
      "cite": "136 S. Ct. 1170"
    },
    {
      "type": "parallel",
      "cite": "194 L. Ed. 2d 192"
    }
  ],
  "court": {
    "name_abbreviation": "U.S.",
    "id": 9009,
    "name": "Supreme Court of the United States"
  },
  "jurisdiction": {
    "id": 39,
    "name_long": "United States",
    "name": "U.S."
  },
  "cites_to": [],
  "analysis": {
    "cardinality": 25,
    "char_count": 194,
    "sha256": "95e4a5c102df1c01c050de5f32940cfc6efd135adeead417698d45f7614efee4",
    "simhash": "1:f8ab20a663cb0591",
    "word_count": 31
  },
  "last_updated": "2021-09-08T21:16:17.237805+00:00",
  "provenance": {
    "date_added": "2021-08-27",
    "source": "Fastcase",
    "batch": "2021"
  },
  "casebody": {
    "judges": [],
    "parties": [
      "Steven Michael BACKSTROM, petitioner,\nv.\nTEXAS."
    ],
    "opinions": [
      {
        "text": "",
        "type": "majority",
        "author": null
      }
    ],
    "attorneys": [
      "Petition for writ of certiorari to the Court of Criminal Appeals of Texas denied."
    ],
    "corrections": "",
    "head_matter": "Steven Michael BACKSTROM, petitioner,\nv.\nTEXAS.\nNo. 15-7157.\nSupreme Court of the United States\nFeb. 29, 2016.\nPetition for writ of certiorari to the Court of Criminal Appeals of Texas denied."
  },
  "file_name": "1170-04",
  "first_page_order": 1170,
  "last_page_order": 1170
}
