{
  "id": 12596131,
  "name": "Ernesto ARELLANO, petitioner, v. Christian PFEIFFER, Acting Warden.",
  "name_abbreviation": "Arellano v. Pfeiffer",
  "decision_date": "2016-03-21",
  "docket_number": "No. 15\u20137779.",
  "first_page": "1464",
  "last_page": "1464",
  "citations": [
    {
      "type": "official",
      "cite": "136 S. Ct. 1464"
    },
    {
      "type": "parallel",
      "cite": "194 L. Ed. 2d 563"
    }
  ],
  "court": {
    "name_abbreviation": "U.S.",
    "id": 9009,
    "name": "Supreme Court of the United States"
  },
  "jurisdiction": {
    "id": 39,
    "name_long": "United States",
    "name": "U.S."
  },
  "cites_to": [],
  "analysis": {
    "cardinality": 28,
    "char_count": 233,
    "sha256": "ad82a354c3c67ca70f0cea4f7832b6a2e2d42f37a977ee2d99f083466935108d",
    "simhash": "1:f3ad74443f0945ac",
    "word_count": 36
  },
  "last_updated": "2021-08-27T21:04:35.133232+00:00",
  "provenance": {
    "date_added": "2021-08-27",
    "source": "Fastcase",
    "batch": "2021"
  },
  "casebody": {
    "judges": [],
    "parties": [
      "Ernesto ARELLANO, petitioner,\nv.\nChristian PFEIFFER, Acting Warden."
    ],
    "opinions": [
      {
        "text": "",
        "type": "majority",
        "author": null
      }
    ],
    "attorneys": [
      "Petition for writ of certiorari to the United States Court of Appeals for the Ninth Circuit denied."
    ],
    "corrections": "",
    "head_matter": "Ernesto ARELLANO, petitioner,\nv.\nChristian PFEIFFER, Acting Warden.\nNo. 15-7779.\nSupreme Court of the United States\nMarch 21, 2016.\nPetition for writ of certiorari to the United States Court of Appeals for the Ninth Circuit denied."
  },
  "file_name": "1464-03",
  "first_page_order": 1464,
  "last_page_order": 1464
}
