{
  "id": 12593447,
  "name": "In re Samuel K. ROBINSON, petitioner.",
  "name_abbreviation": "In re Robinson",
  "decision_date": "2014-10-06",
  "docket_number": "No. 13\u20139904.",
  "first_page": "59",
  "last_page": "59",
  "citations": [
    {
      "type": "official",
      "cite": "135 S. Ct. 59"
    },
    {
      "type": "parallel",
      "cite": "190 L. Ed. 2d 240"
    }
  ],
  "court": {
    "name_abbreviation": "U.S.",
    "id": 9009,
    "name": "Supreme Court of the United States"
  },
  "jurisdiction": {
    "id": 39,
    "name_long": "United States",
    "name": "U.S."
  },
  "cites_to": [],
  "analysis": {
    "cardinality": 23,
    "char_count": 146,
    "sha256": "5513add86fd71247330df09f49acfbac760e218db07a7e0015cef8be0c0880c8",
    "simhash": "1:e2ed9654bc4964e3",
    "word_count": 24
  },
  "last_updated": "2021-08-27T21:04:34.237248+00:00",
  "provenance": {
    "date_added": "2021-08-27",
    "source": "Fastcase",
    "batch": "2021"
  },
  "casebody": {
    "judges": [],
    "parties": [
      "In re Samuel K. ROBINSON, petitioner."
    ],
    "opinions": [
      {
        "text": "Petition for writ of mandamus denied.",
        "type": "majority",
        "author": null
      }
    ],
    "attorneys": [],
    "corrections": "",
    "head_matter": "In re Samuel K. ROBINSON, petitioner.\nNo. 13-9904.\nSupreme Court of the United States\nOct. 6, 2014.\nOpinion"
  },
  "file_name": "0059-06",
  "first_page_order": 59,
  "last_page_order": 59
}
