{
  "id": 12590951,
  "name": "Saqib Bashir KHAN, et vir, petitioners, v. Eric H. HOLDER, Jr., Attorney General.",
  "name_abbreviation": "Khan v. Holder",
  "decision_date": "2014-10-06",
  "docket_number": "No. 14\u201376.",
  "first_page": "244",
  "last_page": "244",
  "citations": [
    {
      "type": "official",
      "cite": "135 S. Ct. 244"
    },
    {
      "type": "parallel",
      "cite": "190 L. Ed. 2d 135"
    }
  ],
  "court": {
    "name_abbreviation": "U.S.",
    "id": 9009,
    "name": "Supreme Court of the United States"
  },
  "jurisdiction": {
    "id": 39,
    "name_long": "United States",
    "name": "U.S."
  },
  "cites_to": [],
  "analysis": {
    "cardinality": 34,
    "char_count": 251,
    "sha256": "88d8cb7df9bc74710cc517dc39598c7e549a3f94c7521fe95f181fa1b430c164",
    "simhash": "1:7b7ff274fde507e8",
    "word_count": 42
  },
  "last_updated": "2021-09-08T21:16:17.237805+00:00",
  "provenance": {
    "date_added": "2021-08-27",
    "source": "Fastcase",
    "batch": "2021"
  },
  "casebody": {
    "judges": [],
    "parties": [
      "Saqib Bashir KHAN, et vir, petitioners,\nv.\nEric H. HOLDER, Jr., Attorney General."
    ],
    "opinions": [
      {
        "text": "Petition for writ of certiorari to the United States Court of Appeals for the Eighth Circuit denied.",
        "type": "majority",
        "author": null
      }
    ],
    "attorneys": [],
    "corrections": "",
    "head_matter": "Saqib Bashir KHAN, et vir, petitioners,\nv.\nEric H. HOLDER, Jr., Attorney General.\nNo. 14-76.\nSupreme Court of the United States\nOct. 6, 2014.\nOpinion"
  },
  "file_name": "0244-03",
  "first_page_order": 244,
  "last_page_order": 244
}
