{
  "id": 12593887,
  "name": "Antonio Rashaad DOVINE, petitioner, v. UNITED STATES.",
  "name_abbreviation": "Dovine v. United States",
  "decision_date": "2014-12-01",
  "docket_number": "No. 14\u20136963.",
  "first_page": "737",
  "last_page": "737",
  "citations": [
    {
      "type": "official",
      "cite": "135 S. Ct. 737"
    },
    {
      "type": "parallel",
      "cite": "190 L. Ed. 2d 460"
    }
  ],
  "court": {
    "name_abbreviation": "U.S.",
    "id": 9009,
    "name": "Supreme Court of the United States"
  },
  "jurisdiction": {
    "id": 39,
    "name_long": "United States",
    "name": "U.S."
  },
  "cites_to": [],
  "analysis": {
    "cardinality": 26,
    "char_count": 225,
    "sha256": "b76bd4fac475cea8840e73eac438f878c5be4a12d4803e8a796a1c9119357203",
    "simhash": "1:7bad46842d884513",
    "word_count": 36
  },
  "last_updated": "2021-09-08T21:16:17.237805+00:00",
  "provenance": {
    "date_added": "2021-08-27",
    "source": "Fastcase",
    "batch": "2021"
  },
  "casebody": {
    "judges": [],
    "parties": [
      "Antonio Rashaad DOVINE, petitioner,\nv.\nUNITED STATES."
    ],
    "opinions": [
      {
        "text": "Petition for writ of certiorari to the United States Court of Appeals for the Fourth Circuit denied.",
        "type": "majority",
        "author": null
      }
    ],
    "attorneys": [],
    "corrections": "",
    "head_matter": "Antonio Rashaad DOVINE, petitioner,\nv.\nUNITED STATES.\nNo. 14-6963.\nSupreme Court of the United States\nDec. 1, 2014.\nOpinion"
  },
  "file_name": "0737-04",
  "first_page_order": 737,
  "last_page_order": 737
}
