{
  "id": 12593970,
  "name": "In re Nathan SMITH, petitioner.",
  "name_abbreviation": "In re Smith",
  "decision_date": "2014-12-01",
  "docket_number": "No. 14\u20135502.",
  "first_page": "748",
  "last_page": "748",
  "citations": [
    {
      "type": "official",
      "cite": "135 S. Ct. 748"
    },
    {
      "type": "parallel",
      "cite": "190 L. Ed. 2d 471"
    }
  ],
  "court": {
    "name_abbreviation": "U.S.",
    "id": 9009,
    "name": "Supreme Court of the United States"
  },
  "jurisdiction": {
    "id": 39,
    "name_long": "United States",
    "name": "U.S."
  },
  "cites_to": [],
  "analysis": {
    "cardinality": 21,
    "char_count": 133,
    "sha256": "58144e156a51f228b0e98d51788fdf01a73d6af9b0d0d26413b642c77e06fbe2",
    "simhash": "1:dbb976843caa640e",
    "word_count": 21
  },
  "last_updated": "2021-08-27T21:04:34.237248+00:00",
  "provenance": {
    "date_added": "2021-08-27",
    "source": "Fastcase",
    "batch": "2021"
  },
  "casebody": {
    "judges": [],
    "parties": [
      "In re Nathan SMITH, petitioner."
    ],
    "opinions": [
      {
        "text": "Petition for rehearing denied.",
        "type": "majority",
        "author": null
      }
    ],
    "attorneys": [],
    "corrections": "",
    "head_matter": "In re Nathan SMITH, petitioner.\nNo. 14-5502.\nSupreme Court of the United States\nDec. 1, 2014.\nOpinion"
  },
  "file_name": "0748-06",
  "first_page_order": 748,
  "last_page_order": 748
}
