{
  "id": 12586872,
  "name": "Otis Lee RODGERS, petitioner, v. CALIFORNIA.",
  "name_abbreviation": "Rodgers v. California",
  "decision_date": "2015-01-12",
  "docket_number": "No. 13\u201310696.",
  "first_page": "1030",
  "last_page": "1030",
  "citations": [
    {
      "type": "official",
      "cite": "135 S. Ct. 1030"
    },
    {
      "type": "parallel",
      "cite": "190 L. Ed. 2d 895"
    }
  ],
  "court": {
    "name_abbreviation": "U.S.",
    "id": 9009,
    "name": "Supreme Court of the United States"
  },
  "jurisdiction": {
    "id": 39,
    "name_long": "United States",
    "name": "U.S."
  },
  "cites_to": [],
  "analysis": {
    "cardinality": 22,
    "char_count": 148,
    "sha256": "9e9e8acc5119bcdd3d34c33f048e662f583e09b5c39a277867170680859865ba",
    "simhash": "1:d58787c43d8462c4",
    "word_count": 22
  },
  "last_updated": "2021-09-08T21:16:17.237805+00:00",
  "provenance": {
    "date_added": "2021-08-27",
    "source": "Fastcase",
    "batch": "2021"
  },
  "casebody": {
    "judges": [],
    "parties": [
      "Otis Lee RODGERS, petitioner,\nv.\nCALIFORNIA."
    ],
    "opinions": [
      {
        "text": "Petition for rehearing denied.",
        "type": "majority",
        "author": null
      }
    ],
    "attorneys": [],
    "corrections": "",
    "head_matter": "Otis Lee RODGERS, petitioner,\nv.\nCALIFORNIA.\nNo. 13-10696.\nSupreme Court of the United States\nJan. 12, 2015.\nOpinion"
  },
  "file_name": "1030-03",
  "first_page_order": 1030,
  "last_page_order": 1030
}
