{
  "id": 12590371,
  "name": "James Gregory SEARS, petitioner, v. Willie THOMAS, Warden, et al.",
  "name_abbreviation": "Sears v. Thomas",
  "decision_date": "2015-05-18",
  "docket_number": "No. 14\u20138820.",
  "first_page": "2317",
  "last_page": "2317",
  "citations": [
    {
      "type": "official",
      "cite": "135 S. Ct. 2317"
    },
    {
      "type": "parallel",
      "cite": "191 L. Ed. 2d 986"
    }
  ],
  "court": {
    "name_abbreviation": "U.S.",
    "id": 9009,
    "name": "Supreme Court of the United States"
  },
  "jurisdiction": {
    "id": 39,
    "name_long": "United States",
    "name": "U.S."
  },
  "cites_to": [],
  "analysis": {
    "cardinality": 31,
    "char_count": 239,
    "sha256": "cd0a1c85085fe5762aed7bbae9d6f9da4467fadf85bca512724ab810cb7f9db5",
    "simhash": "1:79afd6043e0d80c7",
    "word_count": 39
  },
  "last_updated": "2021-08-27T21:04:34.237248+00:00",
  "provenance": {
    "date_added": "2021-08-27",
    "source": "Fastcase",
    "batch": "2021"
  },
  "casebody": {
    "judges": [],
    "parties": [
      "James Gregory SEARS, petitioner,\nv.\nWillie THOMAS, Warden, et al."
    ],
    "opinions": [
      {
        "text": "Petition for writ of certiorari to the United States Court of Appeals for the Eleventh Circuit denied.",
        "type": "majority",
        "author": null
      }
    ],
    "attorneys": [],
    "corrections": "",
    "head_matter": "James Gregory SEARS, petitioner,\nv.\nWillie THOMAS, Warden, et al.\nNo. 14-8820.\nSupreme Court of the United States\nMay 18, 2015.\nOpinion"
  },
  "file_name": "2317-06",
  "first_page_order": 2317,
  "last_page_order": 2317
}
