{
  "id": 12613096,
  "name": "Allen ELLIOTT, petitioner, v. Lorie DAVIS, Director, Texas Department of Criminal Justice, Correctional Institutions Division.",
  "name_abbreviation": "Elliott v. Davis",
  "decision_date": "2017-10-02",
  "docket_number": "No. 17\u20135334.",
  "first_page": "249",
  "last_page": "249",
  "citations": [
    {
      "type": "official",
      "cite": "138 S. Ct. 249"
    },
    {
      "type": "parallel",
      "cite": "199 L. Ed. 2d 161"
    }
  ],
  "court": {
    "name_abbreviation": "U.S.",
    "id": 9009,
    "name": "Supreme Court of the United States"
  },
  "jurisdiction": {
    "id": 39,
    "name_long": "United States",
    "name": "U.S."
  },
  "cites_to": [],
  "analysis": {
    "cardinality": 34,
    "char_count": 290,
    "sha256": "671ce96ab778c8063bbd50ab7c2c2ff9447cd7937b360c7c3147d2707f336c08",
    "simhash": "1:f325726c026c17ed",
    "word_count": 43
  },
  "last_updated": "2021-08-27T21:04:36.906010+00:00",
  "provenance": {
    "date_added": "2021-08-27",
    "source": "Fastcase",
    "batch": "2021"
  },
  "casebody": {
    "judges": [],
    "parties": [
      "Allen ELLIOTT, petitioner,\nv.\nLorie DAVIS, Director, Texas Department of Criminal Justice, Correctional Institutions Division."
    ],
    "opinions": [
      {
        "text": "",
        "type": "majority",
        "author": null
      }
    ],
    "attorneys": [
      "Petition for writ of certiorari to the United States Court of Appeals for the Fifth Circuit denied."
    ],
    "corrections": "",
    "head_matter": "Allen ELLIOTT, petitioner,\nv.\nLorie DAVIS, Director, Texas Department of Criminal Justice, Correctional Institutions Division.\nNo. 17-5334.\nSupreme Court of the United States\nOct. 2, 2017.\nPetition for writ of certiorari to the United States Court of Appeals for the Fifth Circuit denied."
  },
  "file_name": "0249-06",
  "first_page_order": 249,
  "last_page_order": 249
}
