{
  "id": 12626285,
  "name": "Edward SPEARS, petitioner, v. R & R CLEANING SERVICES, et al.",
  "name_abbreviation": "Spears v. R & R Cleaning Servs.",
  "decision_date": "2019-08-05",
  "docket_number": "No. 18\u20138342.",
  "first_page": "19",
  "last_page": "19",
  "citations": [
    {
      "type": "official",
      "cite": "140 S. Ct. 19"
    },
    {
      "type": "parallel",
      "cite": "204 L. Ed. 2d 1175"
    }
  ],
  "court": {
    "name_abbreviation": "U.S.",
    "id": 9009,
    "name": "Supreme Court of the United States"
  },
  "jurisdiction": {
    "id": 39,
    "name_long": "United States",
    "name": "U.S."
  },
  "cites_to": [],
  "analysis": {
    "cardinality": 24,
    "char_count": 156,
    "sha256": "f34bb201f041b15f45e0220b0d92adcad93a2ff93c35b5e03663f30c16e76ab7",
    "simhash": "1:10e714c09e9946d5",
    "word_count": 25
  },
  "last_updated": "2021-08-27T21:04:40.744699+00:00",
  "provenance": {
    "date_added": "2021-08-27",
    "source": "Fastcase",
    "batch": "2021"
  },
  "casebody": {
    "judges": [],
    "parties": [
      "Edward SPEARS, petitioner,\nv.\nR & R CLEANING SERVICES, et al."
    ],
    "opinions": [
      {
        "text": "",
        "type": "majority",
        "author": null
      }
    ],
    "attorneys": [
      "Petition for rehearing denied."
    ],
    "corrections": "",
    "head_matter": "Edward SPEARS, petitioner,\nv.\nR & R CLEANING SERVICES, et al.\nNo. 18-8342.\nSupreme Court of the United States\nAug. 5, 2019.\nPetition for rehearing denied."
  },
  "file_name": "0019-06",
  "first_page_order": 19,
  "last_page_order": 19
}
