{
  "id": 12626131,
  "name": "Martin Arreola ZAVALA, Petitioner v. UNITED STATES.",
  "name_abbreviation": "Zavala v. United States",
  "decision_date": "2019-10-07",
  "docket_number": "No. 18-9677",
  "first_page": "168",
  "last_page": "168",
  "citations": [
    {
      "type": "official",
      "cite": "140 S. Ct. 168"
    },
    {
      "type": "parallel",
      "cite": "205 L. Ed. 2d 104"
    }
  ],
  "court": {
    "name_abbreviation": "U.S.",
    "id": 9009,
    "name": "Supreme Court of the United States"
  },
  "jurisdiction": {
    "id": 39,
    "name_long": "United States",
    "name": "U.S."
  },
  "cites_to": [],
  "analysis": {
    "cardinality": 25,
    "char_count": 218,
    "sha256": "0b9be10b49e3ac823845b820431f5bf277936acc5a24e95d02d793bcd55c56d1",
    "simhash": "1:eaadf64422041301",
    "word_count": 35
  },
  "last_updated": "2021-08-27T21:04:40.744699+00:00",
  "provenance": {
    "date_added": "2021-08-27",
    "source": "Fastcase",
    "batch": "2021"
  },
  "casebody": {
    "judges": [],
    "parties": [
      "Martin Arreola ZAVALA, Petitioner\nv.\nUNITED STATES."
    ],
    "opinions": [
      {
        "text": "",
        "type": "majority",
        "author": null
      }
    ],
    "attorneys": [
      "Petition for writ of certiorari to the United States Court of Appeals for the Eighth Circuit denied."
    ],
    "corrections": "",
    "head_matter": "Martin Arreola ZAVALA, Petitioner\nv.\nUNITED STATES.\nNo. 18-9677\nSupreme Court of the United States.\nOctober 7, 2019\nPetition for writ of certiorari to the United States Court of Appeals for the Eighth Circuit denied."
  },
  "file_name": "0168-05",
  "first_page_order": 168,
  "last_page_order": 168
}
