{
  "id": 12630176,
  "name": "DeAnna MORROW, Petitioner, v. WEST CENTRAL GEORGIA WORKFORCE DEVELOPMENT CORPORATION.",
  "name_abbreviation": "Morrow v. W. Cent. Ga. Workforce Dev. Corp.",
  "decision_date": "2020-01-13",
  "docket_number": "No. 19M82",
  "first_page": "815",
  "last_page": "815",
  "citations": [
    {
      "type": "official",
      "cite": "140 S. Ct. 815"
    },
    {
      "type": "parallel",
      "cite": "205 L. Ed. 2d 452"
    }
  ],
  "court": {
    "name_abbreviation": "U.S.",
    "id": 9009,
    "name": "Supreme Court of the United States"
  },
  "jurisdiction": {
    "id": 39,
    "name_long": "United States",
    "name": "U.S."
  },
  "cites_to": [],
  "analysis": {
    "cardinality": 37,
    "char_count": 255,
    "sha256": "689268ee94220e909f054aa56bf280e3faee7959a52594eef3275886a7b96aaf",
    "simhash": "1:9f8b42269b89f19d",
    "word_count": 41
  },
  "last_updated": "2021-08-27T21:04:40.744699+00:00",
  "provenance": {
    "date_added": "2021-08-27",
    "source": "Fastcase",
    "batch": "2021"
  },
  "casebody": {
    "judges": [],
    "parties": [
      "DeAnna MORROW, Petitioner,\nv.\nWEST CENTRAL GEORGIA WORKFORCE DEVELOPMENT CORPORATION."
    ],
    "opinions": [
      {
        "text": "",
        "type": "majority",
        "author": null
      }
    ],
    "attorneys": [
      "Motion to direct the Clerk to file a petition for writ of certiorari out of time under Rule 14.5 denied."
    ],
    "corrections": "",
    "head_matter": "DeAnna MORROW, Petitioner,\nv.\nWEST CENTRAL GEORGIA WORKFORCE DEVELOPMENT CORPORATION.\nNo. 19M82\nSupreme Court of the United States.\nJanuary 13, 2020\nMotion to direct the Clerk to file a petition for writ of certiorari out of time under Rule 14.5 denied."
  },
  "file_name": "0815-01",
  "first_page_order": 815,
  "last_page_order": 815
}
