{
  "id": 12625620,
  "name": "Anthony Bernard JIMERSON, Petitioner, v. UNITED STATES.",
  "name_abbreviation": "Jimerson v. United States",
  "decision_date": "2020-03-02",
  "docket_number": "No. 18-9796",
  "first_page": "1264",
  "last_page": "1264",
  "citations": [
    {
      "type": "official",
      "cite": "140 S. Ct. 1264"
    },
    {
      "type": "parallel",
      "cite": "206 L. Ed. 2d 254"
    }
  ],
  "court": {
    "name_abbreviation": "U.S.",
    "id": 9009,
    "name": "Supreme Court of the United States"
  },
  "jurisdiction": {
    "id": 39,
    "name_long": "United States",
    "name": "U.S."
  },
  "cites_to": [],
  "analysis": {
    "cardinality": 25,
    "char_count": 222,
    "sha256": "05e0a335162749db19954055b21a607ca3d25f1656c3c175484145e6f4e723ca",
    "simhash": "1:6aaff644370d4259",
    "word_count": 35
  },
  "last_updated": "2021-08-27T21:04:40.744699+00:00",
  "provenance": {
    "date_added": "2021-08-27",
    "source": "Fastcase",
    "batch": "2021"
  },
  "casebody": {
    "judges": [],
    "parties": [
      "Anthony Bernard JIMERSON, Petitioner,\nv.\nUNITED STATES."
    ],
    "opinions": [
      {
        "text": "",
        "type": "majority",
        "author": null
      }
    ],
    "attorneys": [
      "Petition for writ of certiorari to the United States Court of Appeals for the Eleventh Circuit denied."
    ],
    "corrections": "",
    "head_matter": "Anthony Bernard JIMERSON, Petitioner,\nv.\nUNITED STATES.\nNo. 18-9796\nSupreme Court of the United States.\nMarch 2, 2020\nPetition for writ of certiorari to the United States Court of Appeals for the Eleventh Circuit denied."
  },
  "file_name": "1264-02",
  "first_page_order": 1264,
  "last_page_order": 1264
}
