{
  "id": 12607166,
  "name": "GABLES INSURANCE RECOVERY, INC., as Assignee of South Miami Chiropractic LLC, petitioner, v. BLUE CROSS AND BLUE SHIELD OF FLORIDA, INC.",
  "name_abbreviation": "Gables Ins. Recovery, Inc. v. Blue Cross & Blue Shield of Fla., Inc.",
  "decision_date": "2016-10-11",
  "docket_number": "No. 16\u201364.",
  "first_page": "296",
  "last_page": "297",
  "citations": [
    {
      "type": "official",
      "cite": "137 S. Ct. 296"
    },
    {
      "type": "parallel",
      "cite": "196 L. Ed. 2d 215"
    }
  ],
  "court": {
    "name_abbreviation": "U.S.",
    "id": 9009,
    "name": "Supreme Court of the United States"
  },
  "jurisdiction": {
    "id": 39,
    "name_long": "United States",
    "name": "U.S."
  },
  "cites_to": [],
  "analysis": {
    "cardinality": 37,
    "char_count": 302,
    "sha256": "ca08f047a8d7a5941b5729d61706354087e3abca524cb027b181b7f8b86804ee",
    "simhash": "1:3ce756c899a88605",
    "word_count": 49
  },
  "last_updated": "2021-08-27T21:04:35.134644+00:00",
  "provenance": {
    "date_added": "2021-08-27",
    "source": "Fastcase",
    "batch": "2021"
  },
  "casebody": {
    "judges": [],
    "parties": [
      "GABLES INSURANCE RECOVERY, INC., as Assignee of South Miami Chiropractic LLC, petitioner,\nv.\nBLUE CROSS AND BLUE SHIELD OF FLORIDA, INC."
    ],
    "opinions": [
      {
        "text": "",
        "type": "majority",
        "author": null
      }
    ],
    "attorneys": [
      "Petition for writ of certiorari to the United States Court of Appeals for the Eleventh Circuit denied."
    ],
    "corrections": "",
    "head_matter": "GABLES INSURANCE RECOVERY, INC., as Assignee of South Miami Chiropractic LLC, petitioner,\nv.\nBLUE CROSS AND BLUE SHIELD OF FLORIDA, INC.\nNo. 16-64.\nSupreme Court of the United States\nOct. 11, 2016.\nPetition for writ of certiorari to the United States Court of Appeals for the Eleventh Circuit denied."
  },
  "file_name": "0296-06",
  "first_page_order": 296,
  "last_page_order": 297
}
