{
  "id": 12608179,
  "name": "James Chandler RYDER, petitioner, v. Terry ROYAL, Warden.",
  "name_abbreviation": "Ryder v. Royal",
  "decision_date": "2016-11-28",
  "docket_number": "No. 16\u20135970.",
  "first_page": "498",
  "last_page": "498",
  "citations": [
    {
      "type": "official",
      "cite": "137 S. Ct. 498"
    }
  ],
  "court": {
    "name_abbreviation": "U.S.",
    "id": 9009,
    "name": "Supreme Court of the United States"
  },
  "jurisdiction": {
    "id": 39,
    "name_long": "United States",
    "name": "U.S."
  },
  "cites_to": [],
  "analysis": {
    "cardinality": 28,
    "char_count": 222,
    "sha256": "3cdb5f5406821b8ce3c5b23974100a246cccffa4ec018d86245650a521bb0572",
    "simhash": "1:512fd6543b8d95b9",
    "word_count": 36
  },
  "last_updated": "2021-08-27T21:04:35.134644+00:00",
  "provenance": {
    "date_added": "2021-08-27",
    "source": "Fastcase",
    "batch": "2021"
  },
  "casebody": {
    "judges": [],
    "parties": [
      "James Chandler RYDER, petitioner,\nv.\nTerry ROYAL, Warden."
    ],
    "opinions": [
      {
        "text": "",
        "type": "majority",
        "author": null
      }
    ],
    "attorneys": [
      "Petition for writ of certiorari to the United States Court of Appeals for the Tenth Circuit denied."
    ],
    "corrections": "",
    "head_matter": "James Chandler RYDER, petitioner,\nv.\nTerry ROYAL, Warden.\nNo. 16-5970.\nSupreme Court of the United States\nNov. 28, 2016.\nPetition for writ of certiorari to the United States Court of Appeals for the Tenth Circuit denied."
  },
  "file_name": "0498-01",
  "first_page_order": 498,
  "last_page_order": 498
}
