{
  "id": 12604514,
  "name": "Alfredo VASQUEZ-HERNANDEZ, petitioner, v. UNITED STATES.",
  "name_abbreviation": "Vasquez-Hernandez v. United States",
  "decision_date": "2017-04-17",
  "docket_number": "No. 16\u20138249.",
  "first_page": "1600",
  "last_page": "1600",
  "citations": [
    {
      "type": "official",
      "cite": "137 S. Ct. 1600"
    },
    {
      "type": "parallel",
      "cite": "197 L. Ed. 2d 726"
    }
  ],
  "court": {
    "name_abbreviation": "U.S.",
    "id": 9009,
    "name": "Supreme Court of the United States"
  },
  "jurisdiction": {
    "id": 39,
    "name_long": "United States",
    "name": "U.S."
  },
  "cites_to": [],
  "analysis": {
    "cardinality": 24,
    "char_count": 224,
    "sha256": "6c5196e18b791594b4646c2f0a2d01f6e39799486b0a3e72d154708fb35c75aa",
    "simhash": "1:766c76e406068221",
    "word_count": 34
  },
  "last_updated": "2021-09-08T21:16:17.237805+00:00",
  "provenance": {
    "date_added": "2021-08-27",
    "source": "Fastcase",
    "batch": "2021"
  },
  "casebody": {
    "judges": [],
    "parties": [
      "Alfredo VASQUEZ-HERNANDEZ, petitioner,\nv.\nUNITED STATES."
    ],
    "opinions": [
      {
        "text": "",
        "type": "majority",
        "author": null
      }
    ],
    "attorneys": [
      "Petition for writ of certiorari to the United States Court of Appeals for the Seventh Circuit denied."
    ],
    "corrections": "",
    "head_matter": "Alfredo VASQUEZ-HERNANDEZ, petitioner,\nv.\nUNITED STATES.\nNo. 16-8249.\nSupreme Court of the United States\nApril 17, 2017.\nPetition for writ of certiorari to the United States Court of Appeals for the Seventh Circuit denied."
  },
  "file_name": "1600-05",
  "first_page_order": 1600,
  "last_page_order": 1600
}
