{
  "id": 12584965,
  "name": "Manuel Lee PATTON, petitioner, v. UNITED STATES.",
  "name_abbreviation": "Patton v. United States",
  "decision_date": "2013-11-18",
  "docket_number": "No. 13\u20136855.",
  "first_page": "658",
  "last_page": "658",
  "citations": [
    {
      "type": "official",
      "cite": "134 S. Ct. 658"
    },
    {
      "type": "parallel",
      "cite": "187 L. Ed. 2d 435"
    },
    {
      "type": "vendor",
      "cite": "82 U.S.L.W. 3299"
    }
  ],
  "court": {
    "name_abbreviation": "U.S.",
    "id": 9009,
    "name": "Supreme Court of the United States"
  },
  "jurisdiction": {
    "id": 39,
    "name_long": "United States",
    "name": "U.S."
  },
  "cites_to": [],
  "analysis": {
    "cardinality": 25,
    "char_count": 213,
    "sha256": "7d3fa469ca167ecca51ed2d47c3d6c9e9e193c1e19b029b0b70bc2946bbabe17",
    "simhash": "1:f4ad464437a0d629",
    "word_count": 35
  },
  "last_updated": "2021-08-27T21:04:34.235101+00:00",
  "provenance": {
    "date_added": "2021-08-27",
    "source": "Fastcase",
    "batch": "2021"
  },
  "casebody": {
    "judges": [],
    "parties": [
      "Manuel Lee PATTON, petitioner,\nv.\nUNITED STATES."
    ],
    "opinions": [
      {
        "text": "",
        "type": "majority",
        "author": null
      }
    ],
    "attorneys": [
      "Petition for writ of certiorari to the United States Court of Appeals for the Sixth Circuit denied."
    ],
    "corrections": "",
    "head_matter": "Manuel Lee PATTON, petitioner,\nv.\nUNITED STATES.\nNo. 13-6855.\nSupreme Court of the United States\nNov. 18, 2013.\nPetition for writ of certiorari to the United States Court of Appeals for the Sixth Circuit denied."
  },
  "file_name": "0658-01",
  "first_page_order": 658,
  "last_page_order": 658
}
