{
  "id": 12578735,
  "name": "Charles RODRIGUEZ, petitioner, v. Robert WELCH, Warden.",
  "name_abbreviation": "Rodriguez v. Welch",
  "decision_date": "2014-02-24",
  "docket_number": "No. 13\u20138016.",
  "first_page": "1326",
  "last_page": "1326",
  "citations": [
    {
      "type": "official",
      "cite": "134 S. Ct. 1326"
    },
    {
      "type": "parallel",
      "cite": "188 L. Ed. 2d 337"
    },
    {
      "type": "vendor",
      "cite": "82 U.S.L.W. 3493"
    }
  ],
  "court": {
    "name_abbreviation": "U.S.",
    "id": 9009,
    "name": "Supreme Court of the United States"
  },
  "jurisdiction": {
    "id": 39,
    "name_long": "United States",
    "name": "U.S."
  },
  "cites_to": [],
  "analysis": {
    "cardinality": 27,
    "char_count": 220,
    "sha256": "0fe12af52367199d3e6d35e7f9182bd91a6e4f8066e63af249f968d44c5907ec",
    "simhash": "1:7cef54463f01550c",
    "word_count": 35
  },
  "last_updated": "2021-08-27T21:04:34.235101+00:00",
  "provenance": {
    "date_added": "2021-08-27",
    "source": "Fastcase",
    "batch": "2021"
  },
  "casebody": {
    "judges": [],
    "parties": [
      "Charles RODRIGUEZ, petitioner,\nv.\nRobert WELCH, Warden."
    ],
    "opinions": [
      {
        "text": "",
        "type": "majority",
        "author": null
      }
    ],
    "attorneys": [
      "Petition for writ of certiorari to the United States Court of Appeals for the Sixth Circuit denied."
    ],
    "corrections": "",
    "head_matter": "Charles RODRIGUEZ, petitioner,\nv.\nRobert WELCH, Warden.\nNo. 13-8016.\nSupreme Court of the United States\nFeb. 24, 2014.\nPetition for writ of certiorari to the United States Court of Appeals for the Sixth Circuit denied."
  },
  "file_name": "1326-02",
  "first_page_order": 1326,
  "last_page_order": 1326
}
