{
  "id": 12579321,
  "name": "Sammie Lee TAYLOR, petitioner, v. TENNESSEE.",
  "name_abbreviation": "Taylor v. Tennessee",
  "decision_date": "2014-03-10",
  "docket_number": "No. 13\u20138077.",
  "first_page": "1517",
  "last_page": "1517",
  "citations": [
    {
      "type": "official",
      "cite": "134 S. Ct. 1517"
    },
    {
      "type": "parallel",
      "cite": "188 L. Ed. 2d 452"
    },
    {
      "type": "vendor",
      "cite": "82 U.S.L.W. 3527"
    }
  ],
  "court": {
    "name_abbreviation": "U.S.",
    "id": 9009,
    "name": "Supreme Court of the United States"
  },
  "jurisdiction": {
    "id": 39,
    "name_long": "United States",
    "name": "U.S."
  },
  "cites_to": [],
  "analysis": {
    "cardinality": 27,
    "char_count": 215,
    "sha256": "fa6fec6957e3235ed82151d0d4e5ee7a3a44637912bba1e80d56394e12859d26",
    "simhash": "1:68a9360e3bc100f1",
    "word_count": 33
  },
  "last_updated": "2021-08-27T21:04:34.235101+00:00",
  "provenance": {
    "date_added": "2021-08-27",
    "source": "Fastcase",
    "batch": "2021"
  },
  "casebody": {
    "judges": [],
    "parties": [
      "Sammie Lee TAYLOR, petitioner,\nv.\nTENNESSEE."
    ],
    "opinions": [
      {
        "text": "",
        "type": "majority",
        "author": null
      }
    ],
    "attorneys": [
      "Petition for writ of certiorari to the Court of Criminal Appeals of Tennessee, Western Division, denied."
    ],
    "corrections": "",
    "head_matter": "Sammie Lee TAYLOR, petitioner,\nv.\nTENNESSEE.\nNo. 13-8077.\nSupreme Court of the United States\nMarch 10, 2014.\nPetition for writ of certiorari to the Court of Criminal Appeals of Tennessee, Western Division, denied."
  },
  "file_name": "1517-02",
  "first_page_order": 1517,
  "last_page_order": 1517
}
