{
  "id": 12580139,
  "name": "Andrew NAGLY, petitioner, v. MASSACHUSETTS DEPARTMENT OF CHILDREN AND FAMILIES.",
  "name_abbreviation": "Nagly v. Mass. Dep't of Children & Families",
  "decision_date": "2014-04-07",
  "docket_number": "No. 13\u20131017.",
  "first_page": "1798",
  "last_page": "1798",
  "citations": [
    {
      "type": "official",
      "cite": "134 S. Ct. 1798"
    },
    {
      "type": "parallel",
      "cite": "188 L. Ed. 2d 759"
    },
    {
      "type": "vendor",
      "cite": "82 U.S.L.W. 3585"
    }
  ],
  "court": {
    "name_abbreviation": "U.S.",
    "id": 9009,
    "name": "Supreme Court of the United States"
  },
  "jurisdiction": {
    "id": 39,
    "name_long": "United States",
    "name": "U.S."
  },
  "cites_to": [
    {
      "cite": "997 N.E.2d 1220",
      "category": "reporters:state_regional",
      "reporter": "N.E.2d",
      "opinion_index": -1
    }
  ],
  "analysis": {
    "cardinality": 32,
    "char_count": 251,
    "sha256": "33ef52e2a8e2b0bcd23aa7f71f64e36bdec01c76b817dc59f28a929165a8bc7e",
    "simhash": "1:6bef125e3c85c1bf",
    "word_count": 38
  },
  "last_updated": "2024-02-27T18:39:14.938427+00:00",
  "provenance": {
    "date_added": "2021-08-27",
    "source": "Fastcase",
    "batch": "2021"
  },
  "casebody": {
    "judges": [],
    "parties": [
      "Andrew NAGLY, petitioner,\nv.\nMASSACHUSETTS DEPARTMENT OF CHILDREN AND FAMILIES."
    ],
    "opinions": [
      {
        "text": "",
        "type": "majority",
        "author": null
      }
    ],
    "attorneys": [
      "Petition for writ of certiorari to the Appeals Court of Massachusetts denied."
    ],
    "corrections": "",
    "head_matter": "Andrew NAGLY, petitioner,\nv.\nMASSACHUSETTS DEPARTMENT OF CHILDREN AND FAMILIES.\nNo. 13-1017.\nSupreme Court of the United States\nApril 7, 2014.\nCase below, 997 N.E.2d 1220.\nPetition for writ of certiorari to the Appeals Court of Massachusetts denied."
  },
  "file_name": "1798-03",
  "first_page_order": 1798,
  "last_page_order": 1798
}
