{
  "id": 12580336,
  "name": "Adrian M. REQUENA, petitioner, v. Sam CLINE.",
  "name_abbreviation": "Requena v. Cline",
  "decision_date": "2014-04-21",
  "docket_number": "No. 13\u20138599.",
  "first_page": "1881",
  "last_page": "1882",
  "citations": [
    {
      "type": "official",
      "cite": "134 S. Ct. 1881"
    },
    {
      "type": "parallel",
      "cite": "188 L. Ed. 2d 919"
    },
    {
      "type": "vendor",
      "cite": "82 U.S.L.W. 3609"
    }
  ],
  "court": {
    "name_abbreviation": "U.S.",
    "id": 9009,
    "name": "Supreme Court of the United States"
  },
  "jurisdiction": {
    "id": 39,
    "name_long": "United States",
    "name": "U.S."
  },
  "cites_to": [
    {
      "cite": "298 P.3d 1139",
      "category": "reporters:state_regional",
      "reporter": "P.3d",
      "opinion_index": -1
    }
  ],
  "analysis": {
    "cardinality": 31,
    "char_count": 211,
    "sha256": "74205c257f811e606c947b7224f8b189345f0bdfdb7b94e27014b1216c7644ca",
    "simhash": "1:ee7f6404004ba279",
    "word_count": 36
  },
  "last_updated": "2024-02-27T18:39:14.938427+00:00",
  "provenance": {
    "date_added": "2021-08-27",
    "source": "Fastcase",
    "batch": "2021"
  },
  "casebody": {
    "judges": [],
    "parties": [
      "Adrian M. REQUENA, petitioner,\nv.\nSam CLINE."
    ],
    "opinions": [
      {
        "text": "",
        "type": "majority",
        "author": null
      }
    ],
    "attorneys": [
      "Petition for writ of certiorari to the Court of Appeals of Kansas denied."
    ],
    "corrections": "",
    "head_matter": "Adrian M. REQUENA, petitioner,\nv.\nSam CLINE.\nNo. 13-8599.\nSupreme Court of the United States\nApril 21, 2014.\nCase below, 298 P.3d 1139.\nPetition for writ of certiorari to the Court of Appeals of Kansas denied."
  },
  "file_name": "1881-06",
  "first_page_order": 1881,
  "last_page_order": 1882
}
