{
  "id": 12580475,
  "name": "Ronald PAYNE, petitioner, v. DELAWARE.",
  "name_abbreviation": "Payne v. Delaware",
  "decision_date": "2014-04-21",
  "docket_number": "No. 13\u20139112.",
  "first_page": "1903",
  "last_page": "1903",
  "citations": [
    {
      "type": "official",
      "cite": "134 S. Ct. 1903"
    },
    {
      "type": "parallel",
      "cite": "188 L. Ed. 2d 933"
    },
    {
      "type": "vendor",
      "cite": "82 U.S.L.W. 3610"
    }
  ],
  "court": {
    "name_abbreviation": "U.S.",
    "id": 9009,
    "name": "Supreme Court of the United States"
  },
  "jurisdiction": {
    "id": 39,
    "name_long": "United States",
    "name": "U.S."
  },
  "cites_to": [
    {
      "cite": "82 A.3d 730",
      "category": "reporters:state_regional",
      "reporter": "A.3d",
      "opinion_index": -1
    }
  ],
  "analysis": {
    "cardinality": 27,
    "char_count": 202,
    "sha256": "86b8eeb715e84e56f0b273d57cc480d6d8061c34814d6f2bdd0bce22ef741270",
    "simhash": "1:79bf04143a47a3b5",
    "word_count": 33
  },
  "last_updated": "2024-02-27T18:39:14.938427+00:00",
  "provenance": {
    "date_added": "2021-08-27",
    "source": "Fastcase",
    "batch": "2021"
  },
  "casebody": {
    "judges": [],
    "parties": [
      "Ronald PAYNE, petitioner,\nv.\nDELAWARE."
    ],
    "opinions": [
      {
        "text": "",
        "type": "majority",
        "author": null
      }
    ],
    "attorneys": [
      "Petition for writ of certiorari to the Supreme Court of Delaware denied."
    ],
    "corrections": "",
    "head_matter": "Ronald PAYNE, petitioner,\nv.\nDELAWARE.\nNo. 13-9112.\nSupreme Court of the United States\nApril 21, 2014.\nCase below, 82 A.3d 730.\nPetition for writ of certiorari to the Supreme Court of Delaware denied."
  },
  "file_name": "1903-04",
  "first_page_order": 1903,
  "last_page_order": 1903
}
